nosees/__init__.py
nosees/main.py
nosees/plugin.py
nosees/mock/__init__.py
nosees/mock/mock_es.py
nosees/plugin/__init__.py
nosees/plugin/mock_es.py
nosees-0.0.1.dist-info/METADATA
nosees-0.0.1.dist-info/RECORD
nosees-0.0.1.dist-info/WHEEL
nosees-0.0.1.dist-info/entry_points.txt
nosees-0.0.1.dist-info/top_level.txt
