Metadata-Version: 2.1
Name: nosees
Version: 0.0.1
Summary: Replace elaticsearch-py with mock elasticsearch client.
Home-page: UNKNOWN
Author: fatelei
Author-email: fatelei@gmail.com
License: UNKNOWN
Platform: UNKNOWN
Requires-Dist: fake-elasticsearch
Requires-Dist: mock
